git_remote_hg/__init__.py
git_remote_hg/__main__.py
git_remote_hg/_version.py
git_remote_hg/test.py
git_remote_hg3-0.1.1.dist-info/DESCRIPTION.rst
git_remote_hg3-0.1.1.dist-info/METADATA
git_remote_hg3-0.1.1.dist-info/RECORD
git_remote_hg3-0.1.1.dist-info/WHEEL
git_remote_hg3-0.1.1.dist-info/entry_points.txt
git_remote_hg3-0.1.1.dist-info/metadata.json
git_remote_hg3-0.1.1.dist-info/top_level.txt
