Metadata-Version: 2.0
Name: git-remote-hg3
Version: 0.1.1
Summary: access hg repositories as git remotes
Home-page: http://github.com/rfk/git-remote-hg
Author: Ryan Kelly
Author-email: ryan@rfk.id.au
License: MIT
Keywords: git hg mercurial
Platform: UNKNOWN
Classifier: Programming Language :: Python
Classifier: Programming Language :: Python :: 2
Classifier: Programming Language :: Python :: 2.5
Classifier: Programming Language :: Python :: 2.6
Classifier: Programming Language :: Python :: 2.7
Classifier: License :: OSI Approved
Classifier: License :: OSI Approved :: MIT License
Classifier: Development Status :: 4 - Beta
Classifier: Intended Audience :: Developers
Requires-Dist: hg-git
